mpctools/__init__.py
mpctools/extensions/__init__.py
mpctools/extensions/cvext.py
mpctools/extensions/mplext.py
mpctools/extensions/npext.py
mpctools/extensions/pdext.py
mpctools/extensions/skext.py
mpctools/extensions/utils.py
mpctools/parallel/__init__.py
mpctools/parallel/paralleliser.py
mpctools/parallel/progress_bar.py
mpctools-0.14.0.data/data/LICENSE
mpctools-0.14.0.dist-info/LICENSE
mpctools-0.14.0.dist-info/METADATA
mpctools-0.14.0.dist-info/WHEEL
mpctools-0.14.0.dist-info/top_level.txt
mpctools-0.14.0.dist-info/RECORD
