Metadata-Version: 2.1
Name: mpctools
Version: 0.14.0
Summary: A set of tools and utilities for extending common libraries and providing parallel capabilities.
Home-page: https://github.com/michael-camilleri/mpctools
Download-URL: https://github.com/michael-camilleri/mpctools/archive/v_01330.tar.gz
Author: Michael P. J. Camilleri
Author-email: michael.p.camilleri@ed.ac.uk
License: GNU GPL
Keywords: extensions,parallel,utilities
Classifier: Development Status :: 4 - Beta
Classifier: Intended Audience :: Developers
Classifier: Topic :: Software Development :: Libraries
Classifier: License :: OSI Approved :: GNU General Public License (GPL)
Classifier: Programming Language :: Python :: 3 :: Only
License-File: LICENSE
Requires-Dist: scikit-learn
Requires-Dist: matplotlib
Requires-Dist: joblib
Requires-Dist: lapsolver
Requires-Dist: hotelling
Requires-Dist: seaborn
Requires-Dist: pandas
Requires-Dist: pathos
Requires-Dist: scipy
Requires-Dist: numpy
Requires-Dist: numba
Provides-Extra: all
Requires-Dist: torch ; extra == 'all'
Requires-Dist: opencv-python ; extra == 'all'
Provides-Extra: cv
Requires-Dist: opencv-python ; extra == 'cv'
Provides-Extra: torch
Requires-Dist: torch ; extra == 'torch'
